.gitignore
README.md
setup.py
docs/Makefile
docs/conf.py
docs/index.rst
docs/make.bat
docs/_themes/LICENSE
docs/_themes/README.rst
docs/_themes/flask_theme_support.py
docs/_themes/kr/layout.html
docs/_themes/kr/relations.html
docs/_themes/kr/theme.conf
docs/_themes/kr/static/flasky.css_t
docs/_themes/kr/static/small_flask.css
docs/_themes/kr_small/layout.html
docs/_themes/kr_small/theme.conf
docs/_themes/kr_small/static/flasky.css_t
scriptrender/__init__.py
scriptrender/core.py
scriptrender/styles.py
scriptrender/wiki2pdf.py
scriptrender.egg-info/PKG-INFO
scriptrender.egg-info/SOURCES.txt
scriptrender.egg-info/dependency_links.txt
scriptrender.egg-info/not-zip-safe
scriptrender.egg-info/requires.txt
scriptrender.egg-info/top_level.txt
scriptrender/templates/scriptrender.html
tests/__init__.py
tests/render_test.py