Metadata-Version: 1.0
Name: scriptrender
Version: 0.2.1
Summary: Convert wiki pages to pdf and text into images
Home-page: http://silpa.org.in/Render
Author: Santhosh Thottingal
Author-email: santhosh.thottingal@gmail.com
License: LGPL-3.0
Platform: UNKNOWN
